pinggy/__init__.py
pinggy/__main__.py
pinggy/__version__.py
pinggy/core.py
pinggy/loader.py
pinggy/pinggyexception.py
pinggy/pylib.py
pinggy/bin/libpinggy.so
pinggy/bin/openssl/lib/libcrypto.so
pinggy/bin/openssl/lib/libcrypto.so.3
pinggy/bin/openssl/lib/libssl.so
pinggy/bin/openssl/lib/libssl.so.3
pinggy-0.0.19.dist-info/licenses/LICENSE
pinggy-0.0.19.dist-info/METADATA
pinggy-0.0.19.dist-info/WHEEL
pinggy-0.0.19.dist-info/top_level.txt
pinggy-0.0.19.dist-info/RECORD
