Metadata-Version: 2.4
Name: pinggy
Version: 0.0.19
Summary: Tunneling tool
Author: Pinggy
License: Apache 2.0
License-File: LICENSE
Dynamic: author
Dynamic: description
Dynamic: description-content-type
Dynamic: license
Dynamic: license-file
Dynamic: summary
